foo/VERSION
foo/__init__.py
foo/speak.py
foo/version.py
foodemo3-0.0.5.dist-info/LICENSE
foodemo3-0.0.5.dist-info/METADATA
foodemo3-0.0.5.dist-info/WHEEL
foodemo3-0.0.5.dist-info/top_level.txt
foodemo3-0.0.5.dist-info/RECORD
