Metadata-Version: 2.1
Name: foodemo3
Version: 0.0.5
Summary: My DEMO project
Home-page: https://github.com/thieu1995/foodemo
Author: thieu
Author-email: nguyenthieu2102@gmail.com
License: MIT
Keywords: libdemo docs api documentation foo python yaml
Classifier: Development Status :: 5 - Production/Stable
Classifier: License :: OSI Approved :: MIT License
Classifier: Programming Language :: Python :: 3
Classifier: Programming Language :: Python :: 3.7
Classifier: Programming Language :: Python :: 3.8
Classifier: Programming Language :: Python :: 3.9
Classifier: Programming Language :: Python :: 3.10
Classifier: Programming Language :: Python :: 3.11
Classifier: Operating System :: OS Independent
Requires-Python: >=3.5
License-File: LICENSE
Requires-Dist: numpy (>=1.24.2)
